{"updated": "2026-07-24 00:25:02", "usdt_krw": 1463.0, "naver_fx": 1474.9, "stocks": {"SMSN": {"price": 270000.0, "prevClose": 260500.0, "code": "005930", "name": "삼성전자"}, "SKHX": {"price": 1919000.0, "prevClose": 1830000.0, "code": "000660", "name": "SK하이닉스"}}, "indices": {"KOSPI": {"value": 7096.89, "chg": 299.19, "pct": 4.4}, "KOSDAQ": {"value": 790.28, "chg": 39.19, "pct": 5.22}}, "kospi_coef": 41.5533, "etf": [{"code": "0193T0", "name": "KODEX SK하이닉스단일종목레버리지", "brand": "KODEX", "under": "SK하이닉스", "type": "레버리지", "price": 15540.0, "nav": 15664.0, "gap": -0.79, "chgVal": 1360.0, "chgPct": 9.59}, {"code": "0195S0", "name": "TIGER SK하이닉스단일종목레버리지", "brand": "TIGER", "under": "SK하이닉스", "type": "레버리지", "price": 13110.0, "nav": 13208.0, "gap": -0.74, "chgVal": 1120.0, "chgPct": 9.34}, {"code": "0197W0", "name": "SOL SK하이닉스단일종목레버리지", "brand": "SOL", "under": "SK하이닉스", "type": "레버리지", "price": 12965.0, "nav": 13047.0, "gap": -0.63, "chgVal": 1105.0, "chgPct": 9.32}, {"code": "0192L0", "name": "RISE SK하이닉스단일종목레버리지", "brand": "RISE", "under": "SK하이닉스", "type": "레버리지", "price": 13110.0, "nav": 13300.0, "gap": -1.43, "chgVal": 1015.0, "chgPct": 8.39}, {"code": "0194T0", "name": "ACE SK하이닉스단일종목레버리지", "brand": "ACE", "under": "SK하이닉스", "type": "레버리지", "price": 13065.0, "nav": 13181.0, "gap": -0.88, "chgVal": 1095.0, "chgPct": 9.15}, {"code": "0198D0", "name": "1Q SK하이닉스선물단일종목레버리지", "brand": "1Q", "under": "SK하이닉스", "type": "레버리지", "price": 13590.0, "nav": 13756.0, "gap": -1.21, "chgVal": 1085.0, "chgPct": 8.68}, {"code": "0194R0", "name": "KIWOOM SK하이닉스선물단일종목레버리지", "brand": "KIWOOM", "under": "SK하이닉스", "type": "레버리지", "price": 12735.0, "nav": 12855.0, "gap": -0.93, "chgVal": 1170.0, "chgPct": 10.12}, {"code": "0197X0", "name": "SOL SK하이닉스선물단일종목인버스2X", "brand": "SOL", "under": "SK하이닉스", "type": "인버스 2X", "price": 10305.0, "nav": 10202.0, "gap": 1.01, "chgVal": -1045.0, "chgPct": -9.21}, {"code": "0193W0", "name": "KODEX 삼성전자단일종목레버리지", "brand": "KODEX", "under": "삼성전자", "type": "레버리지", "price": 14640.0, "nav": 14725.0, "gap": -0.58, "chgVal": 1020.0, "chgPct": 7.49}, {"code": "0195R0", "name": "TIGER 삼성전자단일종목레버리지", "brand": "TIGER", "under": "삼성전자", "type": "레버리지", "price": 13450.0, "nav": 13534.0, "gap": -0.62, "chgVal": 930.0, "chgPct": 7.43}, {"code": "0193K0", "name": "PLUS 삼성전자단일종목레버리지", "brand": "PLUS", "under": "삼성전자", "type": "레버리지", "price": 14650.0, "nav": 14742.0, "gap": -0.62, "chgVal": 1080.0, "chgPct": 7.96}, {"code": "0192M0", "name": "RISE 삼성전자단일종목레버리지", "brand": "RISE", "under": "삼성전자", "type": "레버리지", "price": 13475.0, "nav": 13661.0, "gap": -1.36, "chgVal": 800.0, "chgPct": 6.31}, {"code": "0194M0", "name": "ACE 삼성전자단일종목레버리지", "brand": "ACE", "under": "삼성전자", "type": "레버리지", "price": 13565.0, "nav": 13579.0, "gap": -0.1, "chgVal": 990.0, "chgPct": 7.87}, {"code": "0198B0", "name": "1Q 삼성전자선물단일종목레버리지", "brand": "1Q", "under": "삼성전자", "type": "레버리지", "price": 13945.0, "nav": 14056.0, "gap": -0.79, "chgVal": 995.0, "chgPct": 7.68}, {"code": "0194N0", "name": "KIWOOM 삼성전자선물단일종목레버리지", "brand": "KIWOOM", "under": "삼성전자", "type": "레버리지", "price": 13250.0, "nav": 13438.0, "gap": -1.4, "chgVal": 930.0, "chgPct": 7.55}, {"code": "0193L0", "name": "PLUS 삼성전자선물단일종목인버스2X", "brand": "PLUS", "under": "삼성전자", "type": "인버스 2X", "price": 15045.0, "nav": 14946.0, "gap": 0.66, "chgVal": -1215.0, "chgPct": -7.47}], "terminal": {"SMSN": {"per": "21.82배", "cnsPer": "5.79배", "pbr": "3.75배", "dvr": null, "eps": "12,372원", "high52": "380,000", "low52": "65,500", "marketValue": "1,578조 4,952억", "frgnRate": "46.71%", "target": "513,958", "recomm": "4.04", "researches": [{"broker": "하나증권", "title": "메모리 이익 체력 확인. 실적 상향 여력 충분", "date": "20260708"}, {"broker": "대신증권", "title": "체급의 위력", "date": "20260708"}, {"broker": "유진투자증권", "title": "걱정의 벽을 타고", "date": "20260708"}, {"broker": "iM증권", "title": "실적 전망치 상향 조정 지속", "date": "20260708"}, {"broker": "IBK투자증권", "title": "외풍을 극복하고도 남을 실적", "date": "20260708"}], "deal": [{"date": "20260723", "frgn": "+1,299,490", "org": "-120,579", "indi": "-1,181,665"}, {"date": "20260722", "frgn": "+2,136,159", "org": "-1,718,094", "indi": "-381,003"}, {"date": "20260721", "frgn": "+1,943,936", "org": "+1,823,763", "indi": "-3,654,326"}, {"date": "20260720", "frgn": "+1,129,083", "org": "-1,468,948", "indi": "+255,913"}, {"date": "20260716", "frgn": "-826,076", "org": "-4,567,849", "indi": "+5,211,886"}]}, "SKHX": {"per": "18.54배", "cnsPer": "6.10배", "pbr": "8.27배", "dvr": null, "eps": "103,521원", "high52": "3,002,000", "low52": "244,000", "marketValue": "1,367조 6,758억", "frgnRate": "52.50%", "target": "3,547,917", "recomm": "4.00", "researches": [{"broker": "미래에셋증권", "title": "시선을 약간만 아래로", "date": "20260714"}, {"broker": "대신증권", "title": "슈퍼 모멘텀", "date": "20260707"}, {"broker": "IBK투자증권", "title": "Agent AI Ecosystem 중심에 서다", "date": "20260702"}, {"broker": "교보증권", "title": "2Q26 Preview 컨센서스 부합", "date": "20260701"}, {"broker": "신한투자증권", "title": "경쟁사 본진으로 침투하는 주도주", "date": "20260630"}], "deal": [{"date": "20260723", "frgn": "+689,697", "org": "-148,136", "indi": "-529,529"}, {"date": "20260722", "frgn": "+640,418", "org": "-564,978", "indi": "-85,833"}, {"date": "20260721", "frgn": "-237,417", "org": "+366,154", "indi": "-116,422"}, {"date": "20260720", "frgn": "+331,597", "org": "-527,040", "indi": "+180,897"}, {"date": "20260716", "frgn": "-469,637", "org": "-628,785", "indi": "+1,067,656"}]}}, "news": [], "filings": [{"ts": "07-23 17:04", "title": "(유가)삼성전자 - 풍문또는보도에대한해명(미확정)", "url": "https://dart.fss.or.kr/api/link.jsp?rcpNo=20260723800875"}, {"ts": "07-22 17:12", "title": "(유가)SK하이닉스 - 신규시설투자등", "url": "https://dart.fss.or.kr/api/link.jsp?rcpNo=20260722800829"}, {"ts": "07-22 09:48", "title": "(유가)SK하이닉스 - 풍문또는보도에대한해명", "url": "https://dart.fss.or.kr/api/link.jsp?rcpNo=20260722800178"}, {"ts": "07-21 16:53", "title": "(유가)삼성전자 - 최대주주등소유주식변동신고서", "url": "https://dart.fss.or.kr/api/link.jsp?rcpNo=20260721801260"}, {"ts": "07-16 17:12", "title": "(유가)삼성전자 - 자기주식처분결과보고서", "url": "https://dart.fss.or.kr/api/link.jsp?rcpNo=20260716000796"}, {"ts": "07-15 15:32", "title": "(유가)SK하이닉스 - 기업설명회(IR)개최(안내공시)", "url": "https://dart.fss.or.kr/api/link.jsp?rcpNo=20260715800456"}, {"ts": "07-15 08:20", "title": "(유가)SK하이닉스 - 유상증자또는주식관련사채등의발행결과(자율공시)", "url": "https://dart.fss.or.kr/api/link.jsp?rcpNo=20260715800045"}, {"ts": "07-15 08:04", "title": "(유가)SK하이닉스 - 증권발행실적보고서", "url": "https://dart.fss.or.kr/api/link.jsp?rcpNo=20260715000004"}, {"ts": "07-13 16:46", "title": "(유가)삼성전자 - 주요사항보고서(자기주식처분결정)", "url": "https://dart.fss.or.kr/api/link.jsp?rcpNo=20260713000395"}, {"ts": "07-13 16:09", "title": "(유가)SK하이닉스 - 주요사항보고서(해외증권시장주권등상장)", "url": "https://dart.fss.or.kr/api/link.jsp?rcpNo=20260713000324"}, {"ts": "07-10 08:26", "title": "(유가)SK하이닉스 - 투자설명서", "url": "https://dart.fss.or.kr/api/link.jsp?rcpNo=20260710000012"}, {"ts": "07-10 08:23", "title": "(유가)SK하이닉스 - [발행조건확정]증권신고서(지분증권)", "url": "https://dart.fss.or.kr/api/link.jsp?rcpNo=20260710000010"}, {"ts": "07-10 08:20", "title": "(유가)SK하이닉스 - [기재정정]주요사항보고서(유상증자결정)", "url": "https://dart.fss.or.kr/api/link.jsp?rcpNo=20260710000008"}, {"ts": "07-10 07:57", "title": "(유가)SK하이닉스 - [기재정정]주요사항보고서(해외증권시장주권등상장결정)", "url": "https://dart.fss.or.kr/api/link.jsp?rcpNo=20260710000002"}, {"ts": "07-10 07:52", "title": "(유가)SK하이닉스 - [기재정정]증권예탁증권(DR)발행결정", "url": "https://dart.fss.or.kr/api/link.jsp?rcpNo=20260710800023"}, {"ts": "07-10 07:30", "title": "(유가)SK하이닉스 - 효력발생안내 ( 2026.6.30. 제출 증권신고서(지분증권) )", "url": "https://dart.fss.or.kr/api/link.jsp?rcpNo=20260630100041"}]}