{"updated": "2026-07-23 08:05:02", "usdt_krw": 1460.0, "naver_fx": 1479.0, "stocks": {"SMSN": {"price": 260500.0, "prevClose": 260500.0, "code": "005930", "name": "삼성전자"}, "SKHX": {"price": 1830000.0, "prevClose": 1830000.0, "code": "000660", "name": "SK하이닉스"}}, "indices": {"KOSPI": {"value": 6797.7, "chg": 0.0, "pct": 0.0}, "KOSDAQ": {"value": 751.09, "chg": 0.0, "pct": 0.0}}, "kospi_coef": 39.7039, "etf": [{"code": "0193T0", "name": "KODEX SK하이닉스단일종목레버리지", "brand": "KODEX", "under": "SK하이닉스", "type": "레버리지", "price": 14180.0, "nav": 14377.0, "gap": -1.37, "chgVal": 0.0, "chgPct": 0.0}, {"code": "0195S0", "name": "TIGER SK하이닉스단일종목레버리지", "brand": "TIGER", "under": "SK하이닉스", "type": "레버리지", "price": 11990.0, "nav": 12122.0, "gap": -1.09, "chgVal": 0.0, "chgPct": 0.0}, {"code": "0197W0", "name": "SOL SK하이닉스단일종목레버리지", "brand": "SOL", "under": "SK하이닉스", "type": "레버리지", "price": 11860.0, "nav": 11982.0, "gap": -1.02, "chgVal": 0.0, "chgPct": 0.0}, {"code": "0192L0", "name": "RISE SK하이닉스단일종목레버리지", "brand": "RISE", "under": "SK하이닉스", "type": "레버리지", "price": 12095.0, "nav": 12288.0, "gap": -1.57, "chgVal": 0.0, "chgPct": 0.0}, {"code": "0194T0", "name": "ACE SK하이닉스단일종목레버리지", "brand": "ACE", "under": "SK하이닉스", "type": "레버리지", "price": 11970.0, "nav": 12095.0, "gap": -1.03, "chgVal": 0.0, "chgPct": 0.0}, {"code": "0198D0", "name": "1Q SK하이닉스선물단일종목레버리지", "brand": "1Q", "under": "SK하이닉스", "type": "레버리지", "price": 12505.0, "nav": 12671.0, "gap": -1.31, "chgVal": 0.0, "chgPct": 0.0}, {"code": "0194R0", "name": "KIWOOM SK하이닉스선물단일종목레버리지", "brand": "KIWOOM", "under": "SK하이닉스", "type": "레버리지", "price": 11565.0, "nav": 11866.0, "gap": -2.54, "chgVal": 0.0, "chgPct": 0.0}, {"code": "0197X0", "name": "SOL SK하이닉스선물단일종목인버스2X", "brand": "SOL", "under": "SK하이닉스", "type": "인버스 2X", "price": 11350.0, "nav": 11353.0, "gap": -0.03, "chgVal": 0.0, "chgPct": 0.0}, {"code": "0193W0", "name": "KODEX 삼성전자단일종목레버리지", "brand": "KODEX", "under": "삼성전자", "type": "레버리지", "price": 13620.0, "nav": 13673.0, "gap": -0.39, "chgVal": 0.0, "chgPct": 0.0}, {"code": "0195R0", "name": "TIGER 삼성전자단일종목레버리지", "brand": "TIGER", "under": "삼성전자", "type": "레버리지", "price": 12520.0, "nav": 12568.0, "gap": -0.38, "chgVal": 0.0, "chgPct": 0.0}, {"code": "0193K0", "name": "PLUS 삼성전자단일종목레버리지", "brand": "PLUS", "under": "삼성전자", "type": "레버리지", "price": 13570.0, "nav": 13722.0, "gap": -1.11, "chgVal": 0.0, "chgPct": 0.0}, {"code": "0192M0", "name": "RISE 삼성전자단일종목레버리지", "brand": "RISE", "under": "삼성전자", "type": "레버리지", "price": 12675.0, "nav": 12694.0, "gap": -0.15, "chgVal": 0.0, "chgPct": 0.0}, {"code": "0194M0", "name": "ACE 삼성전자단일종목레버리지", "brand": "ACE", "under": "삼성전자", "type": "레버리지", "price": 12575.0, "nav": 12633.0, "gap": -0.46, "chgVal": 0.0, "chgPct": 0.0}, {"code": "0198B0", "name": "1Q 삼성전자선물단일종목레버리지", "brand": "1Q", "under": "삼성전자", "type": "레버리지", "price": 12950.0, "nav": 13033.0, "gap": -0.64, "chgVal": 0.0, "chgPct": 0.0}, {"code": "0194N0", "name": "KIWOOM 삼성전자선물단일종목레버리지", "brand": "KIWOOM", "under": "삼성전자", "type": "레버리지", "price": 12320.0, "nav": 12452.0, "gap": -1.06, "chgVal": 0.0, "chgPct": 0.0}, {"code": "0193L0", "name": "PLUS 삼성전자선물단일종목인버스2X", "brand": "PLUS", "under": "삼성전자", "type": "인버스 2X", "price": 16260.0, "nav": 16358.0, "gap": -0.6, "chgVal": 0.0, "chgPct": 0.0}], "terminal": {"SMSN": {"per": "21.06배", "cnsPer": "5.58배", "pbr": "3.62배", "dvr": null, "eps": "12,372원", "high52": "380,000", "low52": "65,500", "marketValue": "1,522조 9,556억", "frgnRate": "46.71%", "target": "513,958", "recomm": "4.04", "researches": [{"broker": "하나증권", "title": "메모리 이익 체력 확인. 실적 상향 여력 충분", "date": "20260708"}, {"broker": "대신증권", "title": "체급의 위력", "date": "20260708"}, {"broker": "유진투자증권", "title": "걱정의 벽을 타고", "date": "20260708"}, {"broker": "iM증권", "title": "실적 전망치 상향 조정 지속", "date": "20260708"}, {"broker": "IBK투자증권", "title": "외풍을 극복하고도 남을 실적", "date": "20260708"}], "deal": [{"date": "20260722", "frgn": "+2,136,159", "org": "-1,718,094", "indi": "-381,003"}, {"date": "20260721", "frgn": "+1,943,936", "org": "+1,823,763", "indi": "-3,654,326"}, {"date": "20260720", "frgn": "+1,129,083", "org": "-1,468,948", "indi": "+255,913"}, {"date": "20260716", "frgn": "-826,076", "org": "-4,567,849", "indi": "+5,211,886"}, {"date": "20260715", "frgn": "+1,799,843", "org": "-413,531", "indi": "-1,363,799"}]}, "SKHX": {"per": "17.68배", "cnsPer": "5.81배", "pbr": "7.89배", "dvr": null, "eps": "103,521원", "high52": "3,002,000", "low52": "244,000", "marketValue": "1,304조 2,453억", "frgnRate": "52.50%", "target": "3,547,917", "recomm": "4.00", "researches": [{"broker": "미래에셋증권", "title": "시선을 약간만 아래로", "date": "20260714"}, {"broker": "대신증권", "title": "슈퍼 모멘텀", "date": "20260707"}, {"broker": "IBK투자증권", "title": "Agent AI Ecosystem 중심에 서다", "date": "20260702"}, {"broker": "교보증권", "title": "2Q26 Preview 컨센서스 부합", "date": "20260701"}, {"broker": "신한투자증권", "title": "경쟁사 본진으로 침투하는 주도주", "date": "20260630"}], "deal": [{"date": "20260722", "frgn": "+640,418", "org": "-564,978", "indi": "-85,833"}, {"date": "20260721", "frgn": "-237,417", "org": "+366,154", "indi": "-116,422"}, {"date": "20260720", "frgn": "+331,597", "org": "-527,040", "indi": "+180,897"}, {"date": "20260716", "frgn": "-469,637", "org": "-628,785", "indi": "+1,067,656"}, {"date": "20260715", "frgn": "+331,145", "org": "+265,930", "indi": "-582,862"}]}}, "news": [{"ts": "07-23 08:00", "epoch": 1784761203, "title": "노태문 사장 \"올해 폴더블폰 3종, 역대 최대 판매 목표\"", "source": "지디넷코리아", "url": "https://news.google.com/rss/articles/CBMiVkFVX3lxTE41a3RaV1JFMzl0NHFQZFdUUWprMGhIN1B5UUdrczV2Y3NjVjdvOXc3WU1xS3Jrc2E5YTJTOFpabnNhTXJHNTBpSkxjdzB3UTFnaTNYY3RR?oc=5", "tags": []}, {"ts": "07-23 08:00", "epoch": 1784761200, "title": "모바일·가전 다음은 '로봇'…삼성전자, DX 미래 먹거리 발굴 '속도'", "source": "청년일보", "url": "https://news.google.com/rss/articles/CBMiZ0FVX3lxTE5ncExnOWJwMHhJZkZKZ2QzYlR6ZEtCblBxZ0NsckNsX05iMll1TV9qdEx3NUFsZ284Y1FrNDhEWEpWMXdLa1dfSlZYb0MwT1RLdV9EdGVBMzdKX25nOHQ2UXJPUk43clk?oc=5", "tags": ["삼성전자"]}, {"ts": "07-23 08:00", "epoch": 1784761200, "title": "삼성전자가 日 최대 게임 개발자 컨퍼런스서 ‘붉은사막’을 시연한 이유는", "source": "뉴데일리", "url": "https://news.google.com/rss/articles/CBMie0FVX3lxTE9sbEVwakMxZ2dFU1RuMmdJdHVOMTQ5d1RUZHEzWlRlT2R0WkZZdGFJOGs5RkdHak1idHZaRFhaOXRqTzhGbUxNZFdtdFZHSW5yNlRadmVYRThCTTljUmxJLWpkTjVfQjlJdzJVeHY5aDhtbW9lS0xfVDh2WdIBgAFBVV95cUxQVE1GZTV1QjBIdjd1TGtOSjcyZUF2OXQ5LU1nY2J0cDJHQkc2Y09KSFdDeXNwcEllOUh4VkpzUFozZlZ4VGY1SFV5SUpicU1KMkpORjA3dVpHSTRCbHdqWHFfcXZuU3l0aTRMU1JFWk9iUVh2QXhrSmpkeGl1ZEJPcQ?oc=5", "tags": ["삼성전자"]}, {"ts": "07-23 08:00", "epoch": 1784761200, "title": "[갤럭시 언팩] \"7년 기술력 쉽게 못 따라와\"…노태문, 폴더블 자신감", "source": "뉴스핌", "url": "https://news.google.com/rss/articles/CBMiXEFVX3lxTE1IYWV5bGhZQnFvVzNpelZKTDdKRlZKcHY1Q0twaXlTcjZVUExuWUxINTV1Y2FYVkNBSFdtSlU1dU1fRlUxcFNRXzN2OUpFdnMyRU5ITTJTSU1Xb2N0?oc=5", "tags": []}, {"ts": "07-23 07:58", "epoch": 1784761080, "title": "[상법개정 1년]③삼성전자·네이버 내년 주총때 이사 선출 놓고 표대결할 수도", "source": "아시아경제", "url": "https://news.google.com/rss/articles/CBMiYEFVX3lxTE1UeEJwTXliNmVXVlpEQ0RPQVhrc0Ezel9BQ1czOTJMMkxDNGtnQWNvMFAxR3BRNl9IYXBubUM3enVHYUlzR19aeXVlZUdzb2RmMDhZX1U5bmRqWkRaYkVNXw?oc=5", "tags": ["삼성전자"]}, {"ts": "07-23 07:57", "epoch": 1784761043, "title": "삼성전자, 폴더블 3종 체제로 승부수…'갤럭시 Z 폴드8 울트라' 첫 공개", "source": "부산경제", "url": "https://news.google.com/rss/articles/CBMib0FVX3lxTE1vU0p4a1ZyRE5xTkZHNVFzb3JEbW1DRURNQ0xJSlQyN0gyWHlMYzkyS1FkbE93M1owUzdiTmlLckVWcEJWSGliNzJpUGRjY0h3RG1tcFhrX0xhR2NTTmVBUG9iaGR3UG9TVlU1eEpwQQ?oc=5", "tags": ["삼성전자"]}, {"ts": "07-23 07:57", "epoch": 1784761043, "title": "삼성, 런던서 언팩 행사…폴드8·첫 스마트글래스 등 공개", "source": "연합뉴스", "url": "https://news.google.com/rss/articles/CBMimgFBVV95cUxPckJSMnYtZU5kWGtoVWxEZmE3aTJfZ3hjVlNBbDJfNG9DQ2g2NjJleGhQUWstX2VUUGRyUXdIOFJucWhtTGxjR01KbC0yYjV5M00zem03Vmd3V1c4UUVINkp1Y3NiV2dpbXdVdXMyUVpaNzFfb2M2YjItbWVGZWx3TWZaVmZXR0VSVDdzNDI2aVVPWlByUGJEMlFB?oc=5", "tags": []}, {"ts": "07-23 07:55", "epoch": 1784760943, "title": "여권 같고 펼치면 책 같고…삼성전자 폴더블 3종", "source": "코리아리포트", "url": "https://news.google.com/rss/articles/CBMicEFVX3lxTFBuSWloS2YxSjRlWVF5RVl6emU4SEdoaUE5b0FlR19PeGZqWWVwLUpSX2RRTGtPRkY5Z3Fxd3lCbkdocnFTQkFnbnoxZjZfeUhuQ2NmYVlNb0ZyM2RENVdwU0xrTlY5bHZsM0Y2WUU5ZXY?oc=5", "tags": ["삼성전자"]}, {"ts": "07-23 07:53", "epoch": 1784760820, "title": "“삼성전자, 구글 AI 최대 수혜주…3개 분기 연속 어닝 서프라이즈 기대”", "source": "매일경제", "url": "https://news.google.com/rss/articles/CBMiUkFVX3lxTE9JaGZ4WW04RHRUMk1PWXl4eExhaGRYX0Ruemo2dzNxVHloUE93QkE3dzVsUzhwbG1scUNwR0FCTkxXVGtRMjBpM3lycGx3TEZMQmc?oc=5", "tags": ["삼성전자"]}, {"ts": "07-23 07:50", "epoch": 1784760617, "title": "\"역대 가장 얇고 가볍다\" 삼성전자, 갤럭시 Z 폴드8·폴드8 울트라·플립8 공개…AI 폴더블 시대 본격 개막", "source": "나눔경제뉴스", "url": "https://news.google.com/rss/articles/CBMibEFVX3lxTE45MXBkNW5ScklvY3UyNWtBR01KUFJsSkluc3RRYmdGdXlSS2dHaEFjLTFMUzNFajYtc1prdnlMM2p6YlZEQ3FSbkl0UFgyU1RHMjd0bEVYSGxnNkk2WDVJcDVBdWNZSk54WTMzeQ?oc=5", "tags": ["삼성전자"]}, {"ts": "07-23 07:49", "epoch": 1784760553, "title": "삼성, 갤럭시 언팩서 구글·퀄컴 협력과 개방성 부각...애플 겨냥", "source": "지디넷코리아", "url": "https://news.google.com/rss/articles/CBMiVkFVX3lxTE91bHNKdVNEWjdycS05YXhwX0Ftbkh4bU5FM0dMdDUtakhoYkhhNF9Ca0tWOGFnM2ROUGtReXdNS1h2THE4MDhVNER2dTRMS2JGNjRJdXN3?oc=5", "tags": []}, {"ts": "07-23 07:44", "epoch": 1784760254, "title": "SK하이닉스 노사, 임단협 집중교섭 재개… 성과급 제도 놓고 이견", "source": "Korea IT Times", "url": "https://news.google.com/rss/articles/CBMicEFVX3lxTFA5S0JkaVE2RFJ2NGpmQ1g1LS0wQ2kxTjliZjg3YjdqMEY1M0pqRG1uTUtFX0dUcVBWWnpmbkJaRlR5ei1WX2RsTUtMV2cyekIzSy1vQ3BhMFNMZ1ByWDA0VDgtV3ZyaWc1N1JuQzRxRW4?oc=5", "tags": ["SK하이닉스"]}, {"ts": "07-23 07:41", "epoch": 1784760080, "title": "삼성전자, ‘갤럭시 Z 폴드8·플립8’ 공개… 에이전트형 AI 탑재", "source": "v.daum.net", "url": "https://news.google.com/rss/articles/CBMiT0FVX3lxTE5WZi1nMG1wT09jdlN5OHdGTjZ2SWVTaVFETHV0Wm52ZEF3WGhSWVBQelJFTGpjUC00bV9kNk11M1NLNTlsRU43MmV5TVVsSG8?oc=5", "tags": ["삼성전자"]}, {"ts": "07-23 07:35", "epoch": 1784759724, "title": "삼성전자, 구글 AI 생태계 최대 수혜주…\"60만전자 간다\"-KB", "source": "edaily.co.kr", "url": "https://news.google.com/rss/articles/CBMigAFBVV95cUxQbENwbWdXNmFrYXowZ3RobDFyeGRuOG9wMnYybzdCdHQ5YzB4cVlBZUZqV0gyWE42QmFzNURMTFMwRFYtTVNnRGpmcHFHajRmTjlYMzVpbHlaN0RFaEg3MVk3TXl0VUxhU1hQQjFnbTdPZ1ZtVDBWWmoySFlrSkdyRA?oc=5", "tags": ["삼성전자"]}, {"ts": "07-23 07:32", "epoch": 1784759555, "title": "삼성전자, 폴더블 ‘울트라’ 시대 연다… 갤럭시 Z8로 AI폰 경쟁 정조준", "source": "Korea IT Times", "url": "https://news.google.com/rss/articles/CBMicEFVX3lxTE5LQzRQTnA4MXdha2tNZng4SlNTM1MwVjVuSW10eVBTNHRFZlhsSzNFV3ZhZFZZYWtoMWxMeUctNUM4Mms2cUlhMnRhNS1IM3doZTduOFNwRXhMM05waTZwbG9vYmItWkQ0STE0VE5fRzE?oc=5", "tags": ["삼성전자"]}, {"ts": "07-23 07:25", "epoch": 1784759147, "title": "삼성전자, AI 헬스케어 품은 '갤럭시 워치9·울트라2' 공개…'사후 대응에서 사전 예방으로'", "source": "열린뉴스통신", "url": "https://news.google.com/rss/articles/CBMiZkFVX3lxTFBERVU2M3FmV0Ztcm85LXROV3dyOE04d2hOWElWMEVBUkJpVHZ3b3RzNS1meENWUDVseGlENl9rTGhLTmhwbW5heG0tblIzdUh6UHpqOTMtcTVuNmJyaTU4cFV6cWpYZw?oc=5", "tags": ["삼성전자"]}, {"ts": "07-23 07:22", "epoch": 1784758920, "title": "“하이닉스, 인텔 오하이오 공장 인수 아닌 협력 가능성”", "source": "이데일리TV", "url": "https://news.google.com/rss/articles/CBMie0FVX3lxTE13eE1TelJEXzNqZjdMZGpVRlRLdGRXTWhIdnVwdnBNT0VENDdWcVFodFRIWlRJX09WamhrYzNQZTBSVVRoTFNfYlUtd0k5R3pET182QTFSbFg1TVVzX25nQzJXS3JDd0VfMXZmOXM3TEdGUG8tS0VmRGxkVQ?oc=5", "tags": ["SK하이닉스"]}, {"ts": "07-23 07:19", "epoch": 1784758745, "title": "﻿'사야 하나 팔아야 하나'…삼전·닉스 롤러코스터에 개미들 깊어지는 고민", "source": "ebn.co.kr", "url": "https://news.google.com/rss/articles/CBMiaEFVX3lxTFBtMnU0QXlFSjdRYUlhdkFBVEFZTmZiemxzTmszUDBxM0ZsWk5ka3NfZDNNbHZramtKWXpZTDVrMDFPb1FOVmJhRXNPRG9DNGI5T0ZNWDZ4VDJjTzVEcG9zM00tQ0F0Skll?oc=5", "tags": []}, {"ts": "07-23 07:16", "epoch": 1784758560, "title": "SK하이닉스, '사업적 자해행위' 하면 안 된다", "source": "OhmyNews", "url": "https://news.google.com/rss/articles/CBMid0FVX3lxTE0zSURBZ3p6bGNmaGI0Mmp1Sk5UYzVVWUVPRndSS051amVwb1BtQ3dDSEo1VGF6SXYwQ282MEdhRzFOd2gxcUtCRGpHWEVLNUZ3Y3dmUUs1SVpFaXYwZ1FZYkg2SVZldFZHMGpieUVFMEE4R1doYnBN?oc=5", "tags": ["SK하이닉스"]}, {"ts": "07-23 07:15", "epoch": 1784758536, "title": "삼성전자, 로봇 사업 ‘전사 총력전’… 휴머노이드 상용화 승부수", "source": "Korea IT Times", "url": "https://news.google.com/rss/articles/CBMicEFVX3lxTFA4ZGxuVW9kVTdzR05vVDVKYl9wQXpHck5IdF9LMVpnMWI4NFl0ek9DSXV3TU1LWXE2aURUT1JnaldWZGd1alVmU1luUXJVUlVGbzRLdnZKQWJ2ZHY4ejBOQTRQb2MwWHdXM3RIa1kwQ18?oc=5", "tags": ["삼성전자"]}, {"ts": "07-23 07:00", "epoch": 1784757652, "title": "SK하이닉스 ADR 환전 랠리에도 원·달러 환율 회귀는 어렵다?", "source": "인베스트조선", "url": "https://news.google.com/rss/articles/CBMickFVX3lxTE9sOHk0RVhzRUNqRVM4SFUxZEpwd0lwc1g2c3ZVMjl3MUkyWkNIMW9NUXktYmZXWndwUWpuOEdkUGtjWDdHN0Zvb2FOaUxiMVZEajhPSmJ4LWhVem1ob0RfUTJldV9KYTRhTjNFU2VqVTdFUQ?oc=5", "tags": ["SK하이닉스"]}, {"ts": "07-23 07:00", "epoch": 1784757625, "title": "SK·삼성·현대차·한화 해외行에 외국계 로펌 서울오피스도 다시 분주", "source": "인베스트조선", "url": "https://news.google.com/rss/articles/CBMigwFBVV95cUxQNDIxajc5VkVOWVVBY2FHeDg1amdvYkk0NW5CZjlaaUdyeHVTWUg5UXd6ZVQxQUlacXE5cUtGTnY3OUNsa1hJSnNHR0g2el9oelliMXpTQnQxSVR3a2FnSkwyc1F0QlhKejMzZzA3MEVqZE9NRzlkUVY5TWVSbTZiM1htaw?oc=5", "tags": []}, {"ts": "07-23 07:00", "epoch": 1784757601, "title": "삼성전자, 로봇 기술·인재 통합 체계 구축해 사업화 시동", "source": "주간동아", "url": "https://news.google.com/rss/articles/CBMiaEFVX3lxTE1GMHVHU3ZTRFlFMUVMNmVVQXhzVmdoa2ZVOGd0ZDJnVlBFblJMMzI1YWZMVThzZTRtdy1BbHFNSTJFelBndVlyZkcxUzRxS040bjV2RXdTaktHVjR5N1FTOVI5RXdoUUQ1?oc=5", "tags": ["삼성전자"]}, {"ts": "07-23 06:55", "epoch": 1784757340, "title": "아산시·삼성전자, HBM 생산공장 증설 맞손…글로벌 반도체 거점 도약 본격화", "source": "오늘경제", "url": "https://news.google.com/rss/articles/CBMic0FVX3lxTE9DMlNHOU1tcXAxdzBPb1hyUTdNT0h1a2EtMzFEY1lmdEJIdjFVczIxTFFDckhsSi1CTmJmMVgyVkZTM1EzMnVWOFU5SE5VMlYyaDY1Q2dDZ09PUWpjaDNTSFhGaTVNQ2tjRjh3azVRQlBSSk0?oc=5", "tags": ["삼성전자"]}, {"ts": "07-23 06:53", "epoch": 1784757182, "title": "SK하이닉스, 인텔 오하이오 공장 ‘인수’ 대신 ‘운영 파트너’ 참여 검토", "source": "엠투데이", "url": "https://news.google.com/rss/articles/CBMib0FVX3lxTE9CV0p2MlNuQTE1R0NfWXM4SkRfc1dEWU11em5ubUNIaUoyeUEzUFJ1ajFmQ0ctQ0RsTl9wQnNuUWN0YkE3Vlpzd21nTmRoMmlILTJyVFN5QmtVT1BQTnJHSXl6clptZnRHUUlTM3pTVdIBc0FVX3lxTE5qVkJlMF8tNDkwdmQ4NEVXSG1OUGYxMlpQVVctcWV0Y0J5aEgtSEs2MjZhOE0ta2VQdU9pX2w5Zm4tVnkwdEdCVFYxQ3JVZlZHSldSazR0REVMNjZieUxxQzBJOUtUZHAxa0JNd2VxdURjRWc?oc=5", "tags": ["SK하이닉스"]}], "filings": [{"ts": "07-22 17:12", "title": "(유가)SK하이닉스 - 신규시설투자등", "url": "https://dart.fss.or.kr/api/link.jsp?rcpNo=20260722800829"}, {"ts": "07-22 09:48", "title": "(유가)SK하이닉스 - 풍문또는보도에대한해명", "url": "https://dart.fss.or.kr/api/link.jsp?rcpNo=20260722800178"}, {"ts": "07-21 16:53", "title": "(유가)삼성전자 - 최대주주등소유주식변동신고서", "url": "https://dart.fss.or.kr/api/link.jsp?rcpNo=20260721801260"}, {"ts": "07-16 17:12", "title": "(유가)삼성전자 - 자기주식처분결과보고서", "url": "https://dart.fss.or.kr/api/link.jsp?rcpNo=20260716000796"}, {"ts": "07-15 15:32", "title": "(유가)SK하이닉스 - 기업설명회(IR)개최(안내공시)", "url": "https://dart.fss.or.kr/api/link.jsp?rcpNo=20260715800456"}, {"ts": "07-15 08:20", "title": "(유가)SK하이닉스 - 유상증자또는주식관련사채등의발행결과(자율공시)", "url": "https://dart.fss.or.kr/api/link.jsp?rcpNo=20260715800045"}, {"ts": "07-15 08:04", "title": "(유가)SK하이닉스 - 증권발행실적보고서", "url": "https://dart.fss.or.kr/api/link.jsp?rcpNo=20260715000004"}, {"ts": "07-13 16:46", "title": "(유가)삼성전자 - 주요사항보고서(자기주식처분결정)", "url": "https://dart.fss.or.kr/api/link.jsp?rcpNo=20260713000395"}, {"ts": "07-13 16:09", "title": "(유가)SK하이닉스 - 주요사항보고서(해외증권시장주권등상장)", "url": "https://dart.fss.or.kr/api/link.jsp?rcpNo=20260713000324"}, {"ts": "07-10 08:26", "title": "(유가)SK하이닉스 - 투자설명서", "url": "https://dart.fss.or.kr/api/link.jsp?rcpNo=20260710000012"}, {"ts": "07-10 08:23", "title": "(유가)SK하이닉스 - [발행조건확정]증권신고서(지분증권)", "url": "https://dart.fss.or.kr/api/link.jsp?rcpNo=20260710000010"}, {"ts": "07-10 08:20", "title": "(유가)SK하이닉스 - [기재정정]주요사항보고서(유상증자결정)", "url": "https://dart.fss.or.kr/api/link.jsp?rcpNo=20260710000008"}, {"ts": "07-10 07:57", "title": "(유가)SK하이닉스 - [기재정정]주요사항보고서(해외증권시장주권등상장결정)", "url": "https://dart.fss.or.kr/api/link.jsp?rcpNo=20260710000002"}, {"ts": "07-10 07:52", "title": "(유가)SK하이닉스 - [기재정정]증권예탁증권(DR)발행결정", "url": "https://dart.fss.or.kr/api/link.jsp?rcpNo=20260710800023"}, {"ts": "07-10 07:30", "title": "(유가)SK하이닉스 - 효력발생안내 ( 2026.6.30. 제출 증권신고서(지분증권) )", "url": "https://dart.fss.or.kr/api/link.jsp?rcpNo=20260630100041"}]}