{"updated": "2026-07-12 10:45:01", "usdt_krw": 1493.0, "naver_fx": 1503.4, "stocks": {"SMSN": {"price": 285000.0, "prevClose": 278000.0, "code": "005930", "name": "삼성전자"}, "SKHX": {"price": 2180000.0, "prevClose": 2186000.0, "code": "000660", "name": "SK하이닉스"}}, "indices": {"KOSPI": {"value": 7475.94, "chg": 184.03, "pct": 2.52}, "KOSDAQ": {"value": 837.43, "chg": 43.43, "pct": 5.47}}, "kospi_coef": 41.1637, "etf": [{"code": "0193T0", "name": "KODEX SK하이닉스단일종목레버리지", "brand": "KODEX", "under": "SK하이닉스", "type": "레버리지", "price": 21760.0, "nav": 21658.0, "gap": 0.47, "chgVal": -170.0, "chgPct": -0.78}, {"code": "0195S0", "name": "TIGER SK하이닉스단일종목레버리지", "brand": "TIGER", "under": "SK하이닉스", "type": "레버리지", "price": 18450.0, "nav": 18345.0, "gap": 0.57, "chgVal": -195.0, "chgPct": -1.05}, {"code": "0197W0", "name": "SOL SK하이닉스단일종목레버리지", "brand": "SOL", "under": "SK하이닉스", "type": "레버리지", "price": 18200.0, "nav": 18110.0, "gap": 0.5, "chgVal": -105.0, "chgPct": -0.57}, {"code": "0192L0", "name": "RISE SK하이닉스단일종목레버리지", "brand": "RISE", "under": "SK하이닉스", "type": "레버리지", "price": 18395.0, "nav": 18383.0, "gap": 0.07, "chgVal": -220.0, "chgPct": -1.18}, {"code": "0194T0", "name": "ACE SK하이닉스단일종목레버리지", "brand": "ACE", "under": "SK하이닉스", "type": "레버리지", "price": 18435.0, "nav": 18291.0, "gap": 0.79, "chgVal": -105.0, "chgPct": -0.57}, {"code": "0198D0", "name": "1Q SK하이닉스선물단일종목레버리지", "brand": "1Q", "under": "SK하이닉스", "type": "레버리지", "price": 19450.0, "nav": 19313.0, "gap": 0.71, "chgVal": -95.0, "chgPct": -0.49}, {"code": "0194R0", "name": "KIWOOM SK하이닉스선물단일종목레버리지", "brand": "KIWOOM", "under": "SK하이닉스", "type": "레버리지", "price": 17765.0, "nav": 17750.0, "gap": 0.08, "chgVal": -155.0, "chgPct": -0.86}, {"code": "0197X0", "name": "SOL SK하이닉스선물단일종목인버스2X", "brand": "SOL", "under": "SK하이닉스", "type": "인버스 2X", "price": 9210.0, "nav": 9274.0, "gap": -0.69, "chgVal": 135.0, "chgPct": 1.49}, {"code": "0193W0", "name": "KODEX 삼성전자단일종목레버리지", "brand": "KODEX", "under": "삼성전자", "type": "레버리지", "price": 17000.0, "nav": 16996.0, "gap": 0.02, "chgVal": 765.0, "chgPct": 4.71}, {"code": "0195R0", "name": "TIGER 삼성전자단일종목레버리지", "brand": "TIGER", "under": "삼성전자", "type": "레버리지", "price": 15635.0, "nav": 15636.0, "gap": -0.01, "chgVal": 710.0, "chgPct": 4.76}, {"code": "0193K0", "name": "PLUS 삼성전자단일종목레버리지", "brand": "PLUS", "under": "삼성전자", "type": "레버리지", "price": 17130.0, "nav": 17000.0, "gap": 0.76, "chgVal": 875.0, "chgPct": 5.38}, {"code": "0192M0", "name": "RISE 삼성전자단일종목레버리지", "brand": "RISE", "under": "삼성전자", "type": "레버리지", "price": 15680.0, "nav": 15752.0, "gap": -0.46, "chgVal": 580.0, "chgPct": 3.84}, {"code": "0194M0", "name": "ACE 삼성전자단일종목레버리지", "brand": "ACE", "under": "삼성전자", "type": "레버리지", "price": 15780.0, "nav": 15698.0, "gap": 0.52, "chgVal": 755.0, "chgPct": 5.02}, {"code": "0198B0", "name": "1Q 삼성전자선물단일종목레버리지", "brand": "1Q", "under": "삼성전자", "type": "레버리지", "price": 16330.0, "nav": 16255.0, "gap": 0.46, "chgVal": 785.0, "chgPct": 5.05}, {"code": "0194N0", "name": "KIWOOM 삼성전자선물단일종목레버리지", "brand": "KIWOOM", "under": "삼성전자", "type": "레버리지", "price": 15405.0, "nav": 15476.0, "gap": -0.46, "chgVal": 610.0, "chgPct": 4.12}, {"code": "0193L0", "name": "PLUS 삼성전자선물단일종목인버스2X", "brand": "PLUS", "under": "삼성전자", "type": "인버스 2X", "price": 14815.0, "nav": 14939.0, "gap": -0.83, "chgVal": -725.0, "chgPct": -4.67}], "terminal": {"SMSN": {"per": "23.04배", "cnsPer": "6.11배", "pbr": "3.96배", "dvr": null, "eps": "12,372원", "high52": "380,000", "low52": "61,100", "marketValue": "1,666조 1,894억", "frgnRate": "46.57%", "target": "513,958", "recomm": "4.04", "researches": [{"broker": "하나증권", "title": "메모리 이익 체력 확인. 실적 상향 여력 충분", "date": "20260708"}, {"broker": "대신증권", "title": "체급의 위력", "date": "20260708"}, {"broker": "유진투자증권", "title": "걱정의 벽을 타고", "date": "20260708"}, {"broker": "iM증권", "title": "실적 전망치 상향 조정 지속", "date": "20260708"}, {"broker": "IBK투자증권", "title": "외풍을 극복하고도 남을 실적", "date": "20260708"}], "deal": [{"date": "20260710", "frgn": "+625,985", "org": "+2,313,745", "indi": "-2,851,466"}, {"date": "20260709", "frgn": "+845,552", "org": "+1,107,761", "indi": "-1,739,937"}, {"date": "20260708", "frgn": "-3,015,093", "org": "+971,031", "indi": "+2,031,705"}, {"date": "20260707", "frgn": "-6,145,090", "org": "-1,852,807", "indi": "+7,870,568"}, {"date": "20260706", "frgn": "-2,018,562", "org": "+14,823", "indi": "+1,917,050"}]}, "SKHX": {"per": "21.06배", "cnsPer": "6.84배", "pbr": "9.17배", "dvr": null, "eps": "103,521원", "high52": "3,002,000", "low52": "244,000", "marketValue": "1,553조 6,912억", "frgnRate": "50.01%", "target": "3,547,917", "recomm": "4.00", "researches": [{"broker": "대신증권", "title": "슈퍼 모멘텀", "date": "20260707"}, {"broker": "IBK투자증권", "title": "Agent AI Ecosystem 중심에 서다", "date": "20260702"}, {"broker": "교보증권", "title": "2Q26 Preview 컨센서스 부합", "date": "20260701"}, {"broker": "신한투자증권", "title": "경쟁사 본진으로 침투하는 주도주", "date": "20260630"}, {"broker": "하나증권", "title": "실적과 멀티플 둘 다 열려 있다", "date": "20260626"}], "deal": [{"date": "20260710", "frgn": "-768,843", "org": "+204,193", "indi": "+550,090"}, {"date": "20260709", "frgn": "-209,485", "org": "+404,365", "indi": "-179,724"}, {"date": "20260708", "frgn": "+88,312", "org": "-285,353", "indi": "+178,421"}, {"date": "20260707", "frgn": "-542,009", "org": "-23,811", "indi": "+553,638"}, {"date": "20260706", "frgn": "-27,696", "org": "-584,423", "indi": "+586,434"}]}}, "news": [{"ts": "07-12 10:40", "epoch": 1783820406, "title": "SK하이닉스, 나스닥 상장 첫날 ADR 12.8% 상승 … 국내 증시에 미칠 영향은?", "source": "스페셜타임스", "url": "https://news.google.com/rss/articles/CBMickFVX3lxTE45S1Bpd2pKNEZJNmd3RlhFWk1XNDhieUwweGdmX05TbmwyZlZIR2VIMUhOVTR3eFhxbGV6S1N6clRmNEJyYWVkQWxwNGVPQmtOSnZRWmV2MXBRYlkzMDlfRHJNQWo0SjhKbUtlSFBKeHZVZw?oc=5", "tags": ["SK하이닉스"]}, {"ts": "07-12 10:36", "epoch": 1783820160, "title": "SK하이닉스 ADR 16% 프리미엄…국내 본주도 재평가 시작되나", "source": "네이트", "url": "https://news.google.com/rss/articles/CBMiU0FVX3lxTE1vcnc1Q19EUm5EMVhybVk0czR6RThZdnN3djVwRm42MlhjV2VFMVdhV0kwSE51Wl84b1V1eHdhbTJtbVFPVDhKem1jWFFreklwNnFn?oc=5", "tags": ["SK하이닉스"]}, {"ts": "07-12 10:30", "epoch": 1783819821, "title": "[IT큐레이션] 40조 실탄 쥔 SK하이닉스가 잊지 말아야 할 나스닥 청구서", "source": "ER 이코노믹리뷰", "url": "https://news.google.com/rss/articles/CBMibEFVX3lxTE83RXlGNDhZNDh5VmtFbzQwVF9UR2pxdGgxY19YLUlOOV9zNFJrd3c2UGJuRUN1MkFWRkwzM242Q29sNnhPTFBoZ2d1Vy16d3JFbDUzaGdoVHlLQ0swMTJtVURLZ1ZlZjViWUFRNA?oc=5", "tags": ["SK하이닉스"]}, {"ts": "07-12 10:26", "epoch": 1783819570, "title": "SK하이닉스 미국 데뷔, 거세진 메모리 피크아웃 논란 [월가백브리핑]", "source": "한국경제", "url": "https://news.google.com/rss/articles/CBMiWkFVX3lxTE1MMFBoa2haSXZpdVNwZjlXd0NOSlY2eV94dkRFb04xU0VOeHpsbVQ5MktNbFpYc2E3YWRjX2hGZllzWklaSEVKSWhDeTMxcjVoaVhDUjRKek1fUdIBVEFVX3lxTFBBMkxGRUh2a212cVB6OHYtU1dRNkFqelFaSjZiS0x6ck1JZU9YSDhrY3ZqVUMyclRPdzFSd1EyMDVObUNNY0loMW93czRCbVM2OGcyTA?oc=5", "tags": ["SK하이닉스"]}, {"ts": "07-12 10:20", "epoch": 1783819200, "title": "SK하이닉스 ADR 상장 첫날 12.8%↑…美 프리미엄, 국내 본주로 이어질까 - 조선비즈", "source": "Chosunbiz", "url": "https://news.google.com/rss/articles/CBMiiAFBVV95cUxPcTJIZTZiMHctWEJwRWUxVURWaVdGVUxjM2FyUlZ2am91ZkZzY0N0Z3oyZHBaTE1Qb1RQdnhxSXVLc3JSWkxfRjY5dFdOeFptaE5RVFkwaUNnMDJXNXk1TnVRTFFTR09pbWwySTRRU2llNldsNGd4eU5fRy1HT3VDSXB5QkMtdlFI0gGcAUFVX3lxTE1SR1dwUXZSdFJGLU9rYndTTUpZRXBiZGNhaUtjTDkwYmtPTjF1NjN1TEVsNWc0emQ1SUVCQmlhbTJDd1M1MWgtcnE5bnZMUzZaUDdBTUJqN2o3SmRUamRmRW11dXZZaWdrM2VwNDItNDNHeHFMNFlGdGNMTnloVXFMUTZ4aUxnTWcwQVVPZTM5WW1PaVlrWW9oc1J1MQ?oc=5", "tags": ["SK하이닉스"]}, {"ts": "07-12 10:18", "epoch": 1783819118, "title": "삼성전자 용인 반도체공장 1∼2년 조기완공…2029년 첫 가동", "source": "뉴스토마토", "url": "https://news.google.com/rss/articles/CBMiYEFVX3lxTE5oNHRPYnZ4M1o1dzB6MHBTMHJObjZFVkNVVGZjU1ByVTA3ZElObHJYUmRyTXB1b2RTMks2SDVFSFFicmJLamhWSW1jNlRadFFtSmU3Ri13YldYY2JSY1pfYw?oc=5", "tags": ["삼성전자"]}, {"ts": "07-12 10:18", "epoch": 1783819106, "title": "삼성전자 용인 반도체 첫 공장 2029년 가동 추진", "source": "전국매일신문", "url": "https://news.google.com/rss/articles/CBMibkFVX3lxTFBGVXhOanRlZ2ExZ1kxMTJBY3oxU2p4VFFuaWk2RXdlSEJmTFdDbE9rNVpfVlI3ZElObzdfd0ZZazJJRlg4aG5vOU1Bdy1sUWFrbXQ3RUFyQklOdE5zVHJBd0FBSDJxM2pYX2pRQzB3?oc=5", "tags": ["삼성전자"]}, {"ts": "07-12 10:08", "epoch": 1783818490, "title": "삼성전자, 용인 1기 팹 1~2년 앞당긴다...‘月 100만 장’ 생산능력 목표", "source": "서울경제신문", "url": "https://news.google.com/rss/articles/CBMiUkFVX3lxTE9maksySDl5MWtlZWNhNnI1SU5QZmRZVG5TVE9kMS1GYzhUakxabmYtM0VlTnZYNXJmZ3NOa1c5S1BmMDZ3ZWlmbndyYWtJbGNDSXc?oc=5", "tags": ["삼성전자"]}, {"ts": "07-12 10:05", "epoch": 1783818352, "title": "SK하이닉스, 美 나스닥 입성···글로벌 AI 반도체 리더십 넓힌다", "source": "서울파이낸스", "url": "https://news.google.com/rss/articles/CBMiakFVX3lxTE16Yi05bjZ3a1UzLWFJQW4td2MyRWN0S25URVJsWC1pa3NmeDF5d24xRk1UN0NWanB6OWdaeVZPMUNFby1yVkNsZVdzbml1UW5IbDZYeWd0NjROUXBmTzRCVkEwY2VETDNNT2c?oc=5", "tags": ["SK하이닉스"]}, {"ts": "07-12 10:02", "epoch": 1783818137, "title": "반도체 급락에 코스피 11%↓…엔터·은행주로 번진 순환매", "source": "마켓인", "url": "https://news.google.com/rss/articles/CBMic0FVX3lxTE1FYUhzdjhSOU44VERhNHBJWHhSSDF2V244d0NfVHJPOFQwSFBwZldERTFiVU9qMVFFc2lMd1lnODJ0c19OY2tZRlJJZjRoR2NpWklrM0VkODBWcWtfQ3Ywa29XVHppX3pJdDFCUU4xLWNFQkE?oc=5", "tags": []}, {"ts": "07-12 10:01", "epoch": 1783818074, "title": "삼성전자 용인 반도체 공장 앞당긴 당긴다…2029년 첫 가동 추진", "source": "전자신문", "url": "https://news.google.com/rss/articles/CBMiTkFVX3lxTFBnc1pxUUFORVBQQ3MyZW9rNFphVEFnZmE4aWNObXpaY0x4TC1oYnhKR0NNbkphU0g0LW40NWNWazVqOU9VY1k1YXpQb0RTdw?oc=5", "tags": ["삼성전자"]}, {"ts": "07-12 09:58", "epoch": 1783817923, "title": "삼성 용인 첫공장 2029년 가동 추진…반도체 투자시계 빨라진다", "source": "스트레이트뉴스", "url": "https://news.google.com/rss/articles/CBMic0FVX3lxTE9OaURCNXRHQUV1WThhZC1QMkZ2TXRFd1ZIUG43SWlCNHpVbjR4VmhrV0MwNEIyWEpWZGd5a1BPWHhLUUJramlwTFB1SWhUQ3VsNVhwRUQ2c0U1ZmpONlBwRlJIRVB4aXdUc0QybmdhZVBYY2_SAXdBVV95cUxQX3pQakp3NFdtSFlidWFEUXVlR2VoMDFUNzlZbEZSeWxTcnh6MUlWU1hhTGRwM19Ld3lJaDZ1c1VGdGVUYVNhTlNoQUNvQmpHNnFSQWJHbWpySnRDWW1pcmJDTWVfRFNBNktPMzFZSlY0RmNxd1czOA?oc=5", "tags": []}, {"ts": "07-12 09:55", "epoch": 1783817716, "title": "삼성전자, 용인 반도체 공장 가동 2년 앞당긴다…2029년 목표", "source": "뉴스1", "url": "https://news.google.com/rss/articles/CBMiZEFVX3lxTE5jTkFYRUN3VmJNVFBKVFdnMVg0NkpoZnA4RWRKS2dCNW1GNllwenNsQUZyNUtoMEEtNkNucE1DVWZzRUE4VzFtbXJiX2x2SGpKZ056akc4dHlSeHpUWTRBU3BTRHg?oc=5", "tags": ["삼성전자"]}, {"ts": "07-12 09:54", "epoch": 1783817651, "title": "삼성, 용인 첫 반도체 공장 2029년 가동 추진…일정 1~2년 앞당긴다", "source": "아주경제", "url": "https://news.google.com/rss/articles/CBMiWkFVX3lxTE5OZHRhOWRRekR5ZUFueDVScWliV3FQSzM2cXFFcFRRVXhsdkNGTlBXVU1lLWpEX0tZSXVvUHluYkt2TXh5Q2pONmNWdkhrc0F2NW5URjNMdGFYUdIBWEFVX3lxTE02bzJtanRVN21yVGwxRUVjSHV6dXRSOUxyOVRMUDE2SlpnOFI4QTNPUE9SRzA2TFg5X0l3M1NTZnpsQUtQa2N5R0kwX3pUUVk1eUxhSURyYU4?oc=5", "tags": []}, {"ts": "07-12 09:51", "epoch": 1783817487, "title": "삼성전자, 용인 클러스터 첫 공장 가동 2년 앞당긴다", "source": "이데일리", "url": "https://news.google.com/rss/articles/CBMigAFBVV95cUxPek5Ia2dkb2I3Q3U1NEU2NTBVa19fMHlJaHhHbFZxMXV3WFFvRGgwS1dZWmVlYS1iTzR2YzVTak5WTzBkRkROdENCa3RnOGlVZmttRGdRdGtQbWxGcmlpeDZvR1MtZURDNG53MFktZFBSTXFJTHhKclBEVTFXUlhMZA?oc=5", "tags": ["삼성전자"]}, {"ts": "07-12 09:51", "epoch": 1783817460, "title": "삼성전자, 용인 클러스터 첫 공장 가동 2년 앞당긴다(종합)", "source": "이데일리TV", "url": "https://news.google.com/rss/articles/CBMie0FVX3lxTE5GRW53ZDE0Q0ZqZWk0bllicTl5RmZWQUVqcXgzUlh3X0R1cGxOU25LWlBTLTJ6d1Z6dF9WTG90aTNoOFpZTWZnWDhFSkswX2lpYS1KTjdJamZQN3FwM0ZUa1g1d0V3SzZMYU5pR2hHNl83M1pwUDA3V1hBUQ?oc=5", "tags": ["삼성전자"]}, {"ts": "07-12 09:47", "epoch": 1783817220, "title": "삼성전자 용인 국가산단 1~2년 앞당긴다…2029년 가동 목표", "source": "이투데이", "url": "https://news.google.com/rss/articles/CBMiVEFVX3lxTE9qSmtkWmpEajQ0dTlxaG9TbmdQeV85WDRTcUtnN3FsaU94V0pvVHBBMklBdXNXT1BMLWVZRVFKQ0NWX1IyVm8wR0RWVEVWd1VtbjlBbA?oc=5", "tags": ["삼성전자"]}, {"ts": "07-12 09:41", "epoch": 1783816860, "title": "[포토뉴스] SK하이닉스, 美 나스닥 입성…자본시장 심장부서 ‘글로벌 컴퍼니’ 위상 높인다", "source": "데일리e뉴스", "url": "https://news.google.com/rss/articles/CBMib0FVX3lxTFBVMmQwVjJNQUU5UVRfV1ZZT0ZzWWNVMW9VS0R2bzVaQ0NZaWRtbWY2bGtFSVcxUFMzYmtkbW1DOFB1NHY1OEVkNVdwdTlxZVFWM2dJQk8yYTExeENJTUtaUlRsbDJlT3IzZ25rTWFoNA?oc=5", "tags": ["SK하이닉스"]}, {"ts": "07-12 09:39", "epoch": 1783816747, "title": "美 나스닥 상장한 SK하이닉스, 고환율 구원투수 될까", "source": "v.daum.net", "url": "https://news.google.com/rss/articles/CBMiT0FVX3lxTE9OQVZRaG9aaEN0ZG9yRnV6d3BpeENOeDlnWUVTektNRWpLRWprQ3IwTW1wemM0aTVxMVp1VG1Jem56SHZCX3kyMjg5WHFGdTA?oc=5", "tags": ["SK하이닉스"]}, {"ts": "07-12 09:35", "epoch": 1783816557, "title": "삼성전자, 용인 반도체 첫 팹 가동 2029년 목표 … 당초 계획보다 최대 2년 앞당긴다", "source": "뉴데일리", "url": "https://news.google.com/rss/articles/CBMie0FVX3lxTFBzSWhxQU1NOVBOUlZmWEU2dU1UeXdlN1FEcVdrLURoTGhrNlBoYUMyNTQ4SWM1UEU2M2dNaURWT2RHbmo5bDhwWXJ2Uy1mZVV6S3RaUDFqWDBhQTJfRUVwUFdVanlEWkVOcEJSTHRaUHFkVGJ4V0lKS3FCa9IBgAFBVV95cUxPa2tmVHcwRUt4aWlkamVDM25RTDJrSEZnTXlqYTZreXpVcUZxdTJzNERRWEVDd1RrYmc4X0p6SGs5VDZoMDlfN2JScFFiY0FPc3NpNmlWcENmck9RVjdpcEY4TC10eUgzd19Qak9DdDV6UFNfXzYzU2k5cUx4VkpOUw?oc=5", "tags": ["삼성전자"]}, {"ts": "07-12 09:28", "epoch": 1783816080, "title": "SK하이닉스 미국서 몸값 더 높았다…국내 증시도 기대감 '솔솔'", "source": "네이트", "url": "https://news.google.com/rss/articles/CBMiU0FVX3lxTE1reGduRldEbTU4TC1od2xlQ19vcEpjTHE2WTZiWVNsanBvcUI3a3JoZkVKM3pxenJ1VDlHZWRKUTdSSXMwZXY3R0xwNElTdUxHeUh3?oc=5", "tags": ["SK하이닉스"]}, {"ts": "07-12 09:27", "epoch": 1783816020, "title": "SK하이닉스 미국서 몸값 더 높았다…국내 증시도 기대감 '솔솔'", "source": "이투데이", "url": "https://news.google.com/rss/articles/CBMiVEFVX3lxTFBkcGZkTlBzZmEzY0VINUp6RDFxaG5RQTh2VVBsaTNwV3N2QWRBaFI3OUpyMERPa1B6VDhvb3Mzd1A0RWRTWlJxeXItdUM4MW5IRjktNA?oc=5", "tags": ["SK하이닉스"]}, {"ts": "07-12 09:22", "epoch": 1783815731, "title": "SK하이닉스 ADR 美서 13% 급등…본주와 16% 가격차, 어떻게 좁혀질까", "source": "이데일리", "url": "https://news.google.com/rss/articles/CBMigAFBVV95cUxPdVk4V213ckZYQkNsMVdRMWNLS2pGcHBseGJXaTVhZUktOXdTTnBHdEI4YkZMTzAwS2pOX29feV9VVzZwMW9KLTlzck1xTUVHeVBJYlJEbkdQNEZpRWdhWnpzZW5hVGRfY1hDUDhEd2d4SFlkZUgtbTZFOHJFQTBKaQ?oc=5", "tags": ["SK하이닉스"]}, {"ts": "07-12 09:22", "epoch": 1783815720, "title": "SK하이닉스 ADR 美서 13% 급등…본주와 16% 가격차, 어떻게 좁혀질까", "source": "이데일리TV", "url": "https://news.google.com/rss/articles/CBMie0FVX3lxTFBUQXlYeVVvazlURlFMWV9IVHZIdU9IVXFwVnFlVXdCVWNBSERwWlFELXNubTk1UXhZQUJaZ1Jvb19zQlZtQXp2Ums1el9BcFA5bW5Rc2JHZi1tU1AwY01HS1hxT0xIQ3EwVnhqeVVXallLNVItWks3ZnNMSQ?oc=5", "tags": ["SK하이닉스"]}, {"ts": "07-12 09:20", "epoch": 1783815600, "title": "SK하이닉스의 40조원 미 나스닥 상장 국내외 4대 로펌 자문", "source": "리걸타임즈", "url": "https://news.google.com/rss/articles/CBMib0FVX3lxTFB0eUlSQ2dTdURPdzVJMHRqbnVNUzVhNWFSUi1TRkwyWDd3dzFJVXRxQ3VjTk9LTi1rX2NWWmdqaXQyLWRSZXBPei1vZmxwZlhXVVFyNG83UDdVX2dma2lVQkNEWXllTHY1Q290QXVZdw?oc=5", "tags": ["SK하이닉스"]}], "filings": [{"ts": "07-10 16:35", "title": "(유가)삼성전자 - 자기주식처분결과보고서", "url": "https://dart.fss.or.kr/api/link.jsp?rcpNo=20260710000585"}, {"ts": "07-10 08:26", "title": "(유가)SK하이닉스 - 투자설명서", "url": "https://dart.fss.or.kr/api/link.jsp?rcpNo=20260710000012"}, {"ts": "07-10 08:23", "title": "(유가)SK하이닉스 - [발행조건확정]증권신고서(지분증권)", "url": "https://dart.fss.or.kr/api/link.jsp?rcpNo=20260710000010"}, {"ts": "07-10 08:20", "title": "(유가)SK하이닉스 - [기재정정]주요사항보고서(유상증자결정)", "url": "https://dart.fss.or.kr/api/link.jsp?rcpNo=20260710000008"}, {"ts": "07-10 07:57", "title": "(유가)SK하이닉스 - [기재정정]주요사항보고서(해외증권시장주권등상장결정)", "url": "https://dart.fss.or.kr/api/link.jsp?rcpNo=20260710000002"}, {"ts": "07-10 07:52", "title": "(유가)SK하이닉스 - [기재정정]증권예탁증권(DR)발행결정", "url": "https://dart.fss.or.kr/api/link.jsp?rcpNo=20260710800023"}, {"ts": "07-10 07:30", "title": "(유가)SK하이닉스 - 효력발생안내 ( 2026.6.30. 제출 증권신고서(지분증권) )", "url": "https://dart.fss.or.kr/api/link.jsp?rcpNo=20260630100041"}]}