{"date": "2026-06-22", "updated": "2026-06-22 06:00", "channels": [{"handle": "taerin", "title": "태린이아빠 주식투자 생각의 공간(26년 6월말 까지)", "count": 0, "private": true}, {"handle": "aicorporateanalysisdeepdive", "title": "AI 리서치 딥다이브_Seoul to Wall St.", "count": 0, "private": false}, {"handle": "shmstory", "title": "시황맨의 주식이야기", "count": 1, "private": false}, {"handle": "bornlupin", "title": "루팡", "count": 0, "private": false}, {"handle": "d_ticker", "title": "딘스티커 Dean's Ticker", "count": 1, "private": false}, {"handle": "ehdwl", "title": "사제콩이_서상영", "count": 0, "private": false}, {"handle": "Macrojunglemicrolens", "title": "Macro Jungle | micro lens", "count": 0, "private": false}, {"handle": "aetherjapanresearch", "title": "에테르의 일본&미국 리서치", "count": 0, "private": false}, {"handle": "athletes_village", "title": "선수촌", "count": 1, "private": false}, {"handle": "sunstudy2222", "title": "선진짱 주식공부방", "count": 0, "private": false}, {"handle": "HANAchina", "title": "하나 중국/신흥국 전략 김경환", "count": 0, "private": false}, {"handle": "cahier_de_market", "title": "카이에 de market", "count": 0, "private": false}, {"handle": "skitteam", "title": "[ IT는 SK ]", "count": 0, "private": false}, {"handle": "free_life59", "title": "프리라이프", "count": 2, "private": false}, {"handle": "Jstockclass", "title": "엄브렐라리서치 Jay의 주식투자교실", "count": 0, "private": false}, {"handle": "ked_epic_ai", "title": "epic AI - 투자 어시스턴트", "count": 0, "private": false}, {"handle": "kkkontemp", "title": "KK Kontemporaries", "count": 0, "private": false}, {"handle": "Joorini34", "title": "Granit34의 투자스토리", "count": 0, "private": false}], "posts": [{"ch": "shmstory", "id": 8635, "ts": "2026-06-22 05:59", "epoch": 1782075557, "text": "6월 22일 시황. 협상으로 시작. 마이크론으로 이어질 주간\n\n주말 미 증시는 휴장. 유럽은 조심스러운 움직임\n미국-이란 종전 합의는 노이즈 이어지는 중\n대면 협상 연기. 이란 재봉쇄 선언. 협상단 다시 파견 등\n특히 이스라엘 공습에 반발해 이란은 해협 재봉쇄 선언\n대면 협상 시작되었으나 트럼프 강경 메세지에 파행\n협상 불발시 더 강하게 공격할 것이라는 SNS 내용\n이란측 강하게 반발해 협상장 이탈했다는 소식\n다만 외신은 이란은 현재 협상 완전 이탈은 아니라고\n협상 자체는 진행 중이라고 보도\n이 점은 어느 정도 예상되었던 측면도\n향 후 협상 과정에서 이런 양상은 지속될 가능성\n그러나 큰 틀이 바뀌지는 않을 것으로 보임\n전쟁 재개가 양측에 큰 부담이 되는 사안\n향 후 산발적인 노이즈성 기사는 이어진다고 봐야\n\n이번주 중동 외 중요한 변수들도 대기 중\n해외는 PCE 물가, 마이크론 실적\n유가 하락으로 PCE 물가 부담은 일단 덜어냄\n최악의 예상 상회 아니라면 단발 요인 정도\n마이크론 실적은 추가 상승 여부를 가늠하는 지표\n최근 목표가 상향이 이어지는 중이었음\n속도 조절론 역시 어느 정도 부각되는 중\n예상치 부합 혹은 어중간한 가이던스 제시하면 부담\n또 셀-온 물량 출회 가능성도 어느 정도 염두\n다만 이전과 다른 업황 사이클로 보는 시각 우세\n일시적 매물 소화 후 추가 상승 가능성 높다는 평가\n실적 발표 전후 변동성은 어느 정도 염두해야\n\n국내는 MSCI 관찰대상국 지정 여부\n일단 증권가 분위기는 쉽지 않다는 분석\n외환 시장 완전 개방 등 일부 조건 미비 등\n지정되지 않는 것이 악재 자체는 아님\n기대감으로 오른 것이 없어 호재 영향력 제한 \n\n최근 증시는 코스피 빅4 중심의 강세 국면\n반면 중소형주, 코스닥은 글로벌 증시 최 약세\n수급 쏠림이 심해지며 빅4 외에는 변동성 혹은 약세\n현재는 포모 국면 더해져 저항대, 목표가는 의미없음\n눌린 코스닥  시장 움직임도 계속 주목은 해야\n지난주 기준 코스닥 PER은 60배 수준\n고점 150배 이상 대비 크게 낮아짐\n60배는 2023년 말 이 후 가장 낮은 수치\n실적 매력은 없지만 하향없이 낙폭 역시 과도\n일부 실적 업종은 반전 가능성도 주시해야\n기존 주도주 관심은 지속 유지해야\n상승 후 눌려 있던 코스닥 종목들 움직임도 주시", "link": "https://t.me/shmstory/8635"}, {"ch": "athletes_village", "id": 22378, "ts": "2026-06-22 01:30", "epoch": 1782059437, "text": "*IRAN SAYS TRUMP'S THREAT HALTED US TALKS IN SWITZERLAND: FARS", "link": "https://t.me/athletes_village/22378"}, {"ch": "free_life59", "id": 48398, "ts": "2026-06-22 00:47", "epoch": 1782056850, "text": "#반도체 #텅스텐\n#메르 님\n\nhttps://m.blog.naver.com/ranto28/224322350093\n\n10. WF₆가스는 DRAM과 NAND 공정 전반에 사용되지만, 쌓는 높이가 높을 수록 사용량이 많아지게 됨.\n\n12. WF₆가스는 HBM과 7나노 이하의 첨단 공정에도 필수로 사용되기때문에 WF₆를 '칩의 혈액(Chip blood)'로 부르고 있음.\n\n14. WF₆가스가 기존에 공급받던 제품과 순도등에 조금만 차이가 나도 수백만달러짜리 웨이퍼가 통째로 못쓰게 되는 경우가 생길수 있음.\n\n15. 공급사를 바꾸는 일이 생각보다 쉬운 일이 아닌것임.\n\n18. 일본기업들은 고순도 텅스텐 분말의 거의 100%를 중국에서 수입해서 왔었고, 중국외 다른 공급처를 구할 수 없었던 것임.\n​\n19. 일본의 간토덴카와 센트럴글래스는 TSMC,삼성,SK하이닉스등 주요고객사에 2026년 7월 1일부터 WF₆공급을 중단한다고 통보함.\n\n33. 텅스텐 생산량은 중국 71,000톤, 베트남 4,800톤, 러시아 2,300톤, 볼리비아 1,400톤 순으로 중국이 약 85%를 차지하고 있음.\n​\n33. 상동광산이 본격 가동되어 연 2,500톤을 생산하면, 한국은 러시아를 제치고 세계 3위 텅스텐 생산국이 될 수 있음.\n​\n34. 상동광산은 캐나다 알몬티가 인수를 했고, 알몬티는 미국 방산업체와 15년 공급계약을 맺고 생산량의 45%를 미국에 공급할 예정임.", "link": "https://t.me/free_life59/48398"}, {"ch": "free_life59", "id": 48397, "ts": "2026-06-22 00:25", "epoch": 1782055518, "text": "#독서 #빌월시 #성적은알아서따라온다\n\nNFL 풋볼이든 권투든 비즈니스든 걸린 보상이 크고 경쟁이 치열한 모든 프로 세계는 다 똑같다. 쓰러지더라도 반드시 다시 일어서야 한다. 일어나 맞서 싸워야 한다.\n\n바닥을 딛고 일어나 다음 움직임을 구상하는 데서 회복과 승리로 향하는 길이 열린다는 점을 기억하라.\n\n.\n\n원동력은 수치화할 수 있는 정말 기본적인 기술이었기에 기초 지능과 성취욕만 있다면 누구나 익힐 수 있다.\n\n어떤 역할이든 관계없이 각자 맡은 일을 정신과 신체 등 모든 기준에서 가능한 한 최고 수준으로 완수하는 것이 우리 팀에 가장 중요했다. 재능이 있더라도 태도가 나쁘면 재능이 없는 것과 마찬가지다.", "link": "https://t.me/free_life59/48397"}, {"ch": "d_ticker", "id": 3285, "ts": "2026-06-22 00:14", "epoch": 1782054869, "text": "25주차 글로벌 증시 주간 상승률 - Dean's Ticker\n\nUS\n+41%｜웨스턴 디지털｜하드디스크\n+32%｜블룸 에너지｜연료전지\n+29%｜네비우스｜네오클라우드\n+29%｜사이퍼 디지털｜AI 인프라\n+29%｜모더나｜바이오\n+28%｜암 홀딩스｜CPU\n+27%｜탈렌 에너지｜발전(원전)\n+24%｜퀀티누움｜양자컴퓨터\n+23%｜인테그리스｜반도체 소재 \n+23%｜시게이트｜하드디스크\n+23%｜코어위브｜네오클라우드\n+23%｜알레그로｜자기·전류 센서 IC\n+22%｜GE버노바｜가스터빈\n+19%｜앰코｜후공정(OSAT)\n+18%｜로블록스｜게임\n+18%｜아르간｜발전소 엔지니어링\n+18%｜MKS 인스투르먼츠｜반도체 장비용 진공부품\n+17%｜로빈후드｜트레이딩 앱\n+17%｜실리콘 모션｜SSD 컨트롤러\n+16%｜샌디스크｜낸드플래시\n+16%｜TTM 테크놀로지스｜PCB\n\nEurope\n+47%｜AT&S｜기판(FC-BGA)\n+35%｜레드케어 파마시｜온라인 의약품\n+25%｜이도르시아｜바이오\n+22%｜노르덱스｜풍력 터빈\n+22%｜SMA 솔라｜태양광 인버터\n+22%｜악토르｜EPC\n+20%｜핀에어｜항공 운송\n+20%｜렌징｜셀롤로오스 섬유\n+19%｜SUSS 마이크로텍｜반도체 본딩 장비\n+19%｜시버스 세미컨덕터｜RF칩\n+19%｜토니즈｜에듀테크\n+18%｜2G 에너지｜발전\n+18%｜아스타 에너지｜변압기 코일·권선\n+16%｜폴리펩타이드 그룹｜의약품위탁생산(CMO)\n+16%｜엘발할코르｜구리 박판\n+16%｜키온 그룹｜물류 자동화 로봇 \n+15%｜도이치방크｜투자은행\n+15%｜에덴레드｜기업 복지 플랫폼\n+15%｜지멘스 에너지｜가스터빈\n+15%｜프리드리히 포어베르크｜가스 파이프라인 건설\n\nJapan\n+49%｜미쓰이 하이텍｜모터 코어\n+37%｜무라타｜수동소자\n+34%｜키옥시아｜메모리\n+33%｜JX 메탈｜반도체·광통신 소재\n+31%｜테크노플렉스｜배관\n+30%｜J.S.B.｜부동산\n+29%｜메이코｜PCB\n+29%｜이비덴 ｜기판(FC-BGA)\n+27%｜세이코기켄｜광통신부품\n+27%｜후루카와｜광케이블\n+25%｜레이저텍｜마스크 검사 장비\n+25%｜산텍｜광 측정기\n+23%｜스미토모 일렉트릭｜광통신부품·소재\n+23%｜산키 엔지니어링｜클린룸 공사\n+23%｜타이오유덴｜수동소자\n+22%｜킨덴｜전력망 엔지니어링\n+21%｜후지쿠라｜광케이블\n+21%｜탐론｜광학 렌즈\n+21%｜신포니아｜웨이퍼 반송 장비(EFEM)\n+21%｜덱세리얼즈｜이방성도전필름(ACF)\n+21%｜메이덴샤｜변압기\n+20%｜스크린 홀딩스｜반도체 세정 장비\n+20%｜NGK 인슐레이터｜전력망 절연체\n\nKorea\n+34%｜가온전선｜케이블\n+34%｜삼화콘덴서｜수동소자\n+32%｜삼성전기｜수동소자·기판\n+31%｜SK스퀘어｜투자사\n+29%｜삼성생명｜보험\n+29%｜SK하이닉스｜메모리\n+27%｜디앤디파마텍｜바이오\n+22%｜SK｜지주사\n+22%｜미래에셋생명｜보험\n+16%｜LS일렉트릭｜전력기기\n+15%｜올릭스｜바이오\n+14%｜효성중공업｜전력기기\n+14%｜한화오션｜선박\n+14%｜삼성물산｜건설\n+13%｜한화엔진｜디제엔진\n+12%｜제주반도체｜메모리\n+11%｜SK리츠｜리츠\n+11%｜LG이노텍｜기판(FC-BGA)\n+10%｜달바글로벌｜화장품\n\n※ 시가총액 $1B 이상만 분류 (US는 $10B 이상)", "link": "https://t.me/d_ticker/3285"}], "errors": []}